pdfid/__init__.py
pdfid/__main__.py
pdfid/pdfid.py
pdfid-1.1.2.dist-info/LICENSE
pdfid-1.1.2.dist-info/METADATA
pdfid-1.1.2.dist-info/WHEEL
pdfid-1.1.2.dist-info/top_level.txt
pdfid-1.1.2.dist-info/RECORD
