Metadata-Version: 2.1
Name: pdfid
Version: 1.1.2
Summary: PDFID simple tool to analyze PDF malicious files by DidierStevens. Customized by Matteo Lodi to be used as a library.
Home-page: https://github.com/mlodic/pdfid
Author: Matteo Lodi
Classifier: License :: OSI Approved :: MIT License
Classifier: Programming Language :: Python
Requires-Python: >=2.6, <4
License-File: LICENSE
